{
  "app": "crm",
  "module": "finance",
  "version": "2.1.0-ext",
  "merge_into": "_index.json",
  "skills": [
    { "name": "input_invoices_summary", "description": "Tổng quan HĐ đầu vào.", "endpoint": "POST /internal/skills/input_invoices_summary", "input_schema": { "type": "object", "properties": { "period": { "type": "string" } } }, "type": "action", "risk_level": "read" },
    { "name": "create_input_invoice", "description": "Tạo HĐ đầu vào.", "endpoint": "POST /internal/skills/create_input_invoice", "input_schema": { "type": "object", "required": ["supplier_id", "items"], "properties": { "supplier_id": { "type": "string" }, "items": { "type": "array" }, "vat_percent": { "type": "number" }, "invoice_no": { "type": "string" }, "date": { "type": "string", "format": "date" } } }, "type": "action", "risk_level": "high" },
    { "name": "get_input_invoice_detail", "description": "Chi tiết HĐ đầu vào.", "endpoint": "POST /internal/skills/get_input_invoice_detail", "input_schema": { "type": "object", "required": ["invoice_id"], "properties": { "invoice_id": { "type": "string" } } }, "type": "action", "risk_level": "read" },
    { "name": "update_input_invoice", "description": "Sửa HĐ đầu vào.", "endpoint": "POST /internal/skills/update_input_invoice", "input_schema": { "type": "object", "required": ["invoice_id"], "properties": { "invoice_id": { "type": "string" } } }, "type": "action", "risk_level": "normal" },
    { "name": "delete_input_invoice", "description": "Xóa HĐ đầu vào.", "endpoint": "POST /internal/skills/delete_input_invoice", "input_schema": { "type": "object", "required": ["invoice_id"], "properties": { "invoice_id": { "type": "string" }, "reason": { "type": "string" } } }, "type": "action", "risk_level": "high" },
    { "name": "pay_input_invoice", "description": "Thanh toán HĐ NCC.", "endpoint": "POST /internal/skills/pay_input_invoice", "input_schema": { "type": "object", "required": ["invoice_id", "amount", "method"], "properties": { "invoice_id": { "type": "string" }, "amount": { "type": "number" }, "method": { "type": "string", "enum": ["CASH", "TRANSFER", "CARD"] } } }, "type": "action", "risk_level": "high" },
    { "name": "list_input_invoice_payments", "description": "Lịch sử thanh toán HĐ đầu vào.", "endpoint": "POST /internal/skills/list_input_invoice_payments", "input_schema": { "type": "object", "required": ["invoice_id"], "properties": { "invoice_id": { "type": "string" } } }, "type": "action", "risk_level": "read" },
    { "name": "cashbook_balance", "description": "Số dư quỹ tại thời điểm.", "endpoint": "POST /internal/skills/cashbook_balance", "input_schema": { "type": "object", "properties": { "as_of_date": { "type": "string", "format": "date" }, "payment_method": { "type": "string" } } }, "type": "action", "risk_level": "read" },
    { "name": "update_cashbook_entry", "description": "Sửa phiếu thu/chi.", "endpoint": "POST /internal/skills/update_cashbook_entry", "input_schema": { "type": "object", "required": ["entry_id"], "properties": { "entry_id": { "type": "string" } } }, "type": "action", "risk_level": "normal" },
    { "name": "delete_cashbook_entry", "description": "Xóa phiếu.", "endpoint": "POST /internal/skills/delete_cashbook_entry", "input_schema": { "type": "object", "required": ["entry_id"], "properties": { "entry_id": { "type": "string" }, "reason": { "type": "string" } } }, "type": "action", "risk_level": "high" },
    { "name": "get_cashbook_entry", "description": "Chi tiết phiếu.", "endpoint": "POST /internal/skills/get_cashbook_entry", "input_schema": { "type": "object", "required": ["entry_id"], "properties": { "entry_id": { "type": "string" } } }, "type": "action", "risk_level": "read" },
    { "name": "transfer_between_accounts", "description": "Chuyển quỹ TM ↔ NH.", "endpoint": "POST /internal/skills/transfer_between_accounts", "input_schema": { "type": "object", "required": ["from_method", "to_method", "amount"], "properties": { "from_method": { "type": "string" }, "to_method": { "type": "string" }, "amount": { "type": "number" }, "note": { "type": "string" } } }, "type": "action", "risk_level": "high" },
    { "name": "bank_reconciliation", "description": "Đối soát sao kê NH.", "endpoint": "POST /internal/skills/bank_reconciliation", "input_schema": { "type": "object", "required": ["statement_file_url", "account_id"], "properties": { "statement_file_url": { "type": "string" }, "account_id": { "type": "string" } } }, "type": "action", "risk_level": "high" },
    { "name": "export_cashbook", "description": "Export sổ quỹ.", "endpoint": "POST /internal/skills/export_cashbook", "input_schema": { "type": "object", "properties": { "period": { "type": "string" }, "format": { "type": "string", "default": "xlsx" } } }, "type": "action", "risk_level": "read" },
    { "name": "debts_summary", "description": "Tổng quan công nợ.", "endpoint": "POST /internal/skills/debts_summary", "input_schema": { "type": "object", "properties": {} }, "type": "action", "risk_level": "read" },
    { "name": "list_customer_debts", "description": "Công nợ của 1 KH.", "endpoint": "POST /internal/skills/list_customer_debts", "input_schema": { "type": "object", "required": ["person_id"], "properties": { "person_id": { "type": "string" } } }, "type": "action", "risk_level": "read" },
    { "name": "list_debt_payments", "description": "Lịch sử thu nợ.", "endpoint": "POST /internal/skills/list_debt_payments", "input_schema": { "type": "object", "properties": { "period": { "type": "string" }, "person_id": { "type": "string" } } }, "type": "action", "risk_level": "read" },
    { "name": "send_debt_reminder", "description": "Gửi nhắc nợ Zalo.", "endpoint": "POST /internal/skills/send_debt_reminder", "input_schema": { "type": "object", "properties": { "person_id": { "type": "string" }, "person_ids": { "type": "array", "items": { "type": "string" } }, "template_id": { "type": "string" } } }, "type": "action", "risk_level": "normal" },
    { "name": "write_off_debt", "description": "Xóa khoản nợ (write-off).", "endpoint": "POST /internal/skills/write_off_debt", "input_schema": { "type": "object", "required": ["debt_id", "reason"], "properties": { "debt_id": { "type": "string" }, "reason": { "type": "string" } } }, "type": "action", "risk_level": "high" },
    { "name": "export_debts", "description": "Export công nợ.", "endpoint": "POST /internal/skills/export_debts", "input_schema": { "type": "object", "properties": { "filter": { "type": "object" } } }, "type": "action", "risk_level": "read" },
    { "name": "refunds_summary", "description": "Tổng quan hoàn tiền.", "endpoint": "POST /internal/skills/refunds_summary", "input_schema": { "type": "object", "properties": { "period": { "type": "string" } } }, "type": "action", "risk_level": "read" },
    { "name": "list_refunds", "description": "List phiếu hoàn.", "endpoint": "POST /internal/skills/list_refunds", "input_schema": { "type": "object", "properties": { "status": { "type": "string", "enum": ["PENDING", "APPROVED", "REJECTED", "COMPLETED", "ALL"] } } }, "type": "action", "risk_level": "read" },
    { "name": "get_refund_detail", "description": "Chi tiết phiếu hoàn.", "endpoint": "POST /internal/skills/get_refund_detail", "input_schema": { "type": "object", "required": ["refund_id"], "properties": { "refund_id": { "type": "string" } } }, "type": "action", "risk_level": "read" },
    { "name": "approve_refund", "description": "Duyệt hoàn.", "endpoint": "POST /internal/skills/approve_refund", "input_schema": { "type": "object", "required": ["refund_id"], "properties": { "refund_id": { "type": "string" }, "approver_note": { "type": "string" } } }, "type": "action", "risk_level": "high" },
    { "name": "reject_refund", "description": "Từ chối hoàn.", "endpoint": "POST /internal/skills/reject_refund", "input_schema": { "type": "object", "required": ["refund_id", "reason"], "properties": { "refund_id": { "type": "string" }, "reason": { "type": "string" } } }, "type": "action", "risk_level": "normal" },
    { "name": "complete_refund", "description": "Hoàn tất trả tiền.", "endpoint": "POST /internal/skills/complete_refund", "input_schema": { "type": "object", "required": ["refund_id", "actual_method", "actual_amount"], "properties": { "refund_id": { "type": "string" }, "actual_method": { "type": "string" }, "actual_amount": { "type": "number" } } }, "type": "action", "risk_level": "high" },
    { "name": "update_refund", "description": "Sửa phiếu hoàn.", "endpoint": "POST /internal/skills/update_refund", "input_schema": { "type": "object", "required": ["refund_id"], "properties": { "refund_id": { "type": "string" } } }, "type": "action", "risk_level": "normal" },
    { "name": "delete_refund", "description": "Xóa phiếu hoàn.", "endpoint": "POST /internal/skills/delete_refund", "input_schema": { "type": "object", "required": ["refund_id"], "properties": { "refund_id": { "type": "string" }, "reason": { "type": "string" } } }, "type": "action", "risk_level": "high" },
    { "name": "list_refund_approvals", "description": "Lịch sử duyệt hoàn.", "endpoint": "POST /internal/skills/list_refund_approvals", "input_schema": { "type": "object", "required": ["refund_id"], "properties": { "refund_id": { "type": "string" } } }, "type": "action", "risk_level": "read" },
    { "name": "update_marketing_cost", "description": "Sửa chi phí MKT.", "endpoint": "POST /internal/skills/update_marketing_cost", "input_schema": { "type": "object", "required": ["cost_id"], "properties": { "cost_id": { "type": "string" } } }, "type": "action", "risk_level": "normal" },
    { "name": "delete_marketing_cost", "description": "Xóa.", "endpoint": "POST /internal/skills/delete_marketing_cost", "input_schema": { "type": "object", "required": ["cost_id"], "properties": { "cost_id": { "type": "string" }, "reason": { "type": "string" } } }, "type": "action", "risk_level": "high" },
    { "name": "approve_marketing_cost", "description": "Duyệt chi phí MKT.", "endpoint": "POST /internal/skills/approve_marketing_cost", "input_schema": { "type": "object", "required": ["cost_id"], "properties": { "cost_id": { "type": "string" } } }, "type": "action", "risk_level": "normal" },
    { "name": "reject_marketing_cost", "description": "Từ chối.", "endpoint": "POST /internal/skills/reject_marketing_cost", "input_schema": { "type": "object", "required": ["cost_id", "reason"], "properties": { "cost_id": { "type": "string" }, "reason": { "type": "string" } } }, "type": "action", "risk_level": "normal" },
    { "name": "get_marketing_cost_detail", "description": "Chi tiết.", "endpoint": "POST /internal/skills/get_marketing_cost_detail", "input_schema": { "type": "object", "required": ["cost_id"], "properties": { "cost_id": { "type": "string" } } }, "type": "action", "risk_level": "read" },
    { "name": "update_payment_method", "description": "Sửa PTTT.", "endpoint": "POST /internal/skills/update_payment_method", "input_schema": { "type": "object", "required": ["pttt_id"], "properties": { "pttt_id": { "type": "string" } } }, "type": "action", "risk_level": "normal" },
    { "name": "delete_payment_method", "description": "Xóa PTTT.", "endpoint": "POST /internal/skills/delete_payment_method", "input_schema": { "type": "object", "required": ["pttt_id"], "properties": { "pttt_id": { "type": "string" } } }, "type": "action", "risk_level": "high" },
    { "name": "set_default_payment_method", "description": "Đặt mặc định.", "endpoint": "POST /internal/skills/set_default_payment_method", "input_schema": { "type": "object", "required": ["pttt_id"], "properties": { "pttt_id": { "type": "string" } } }, "type": "action", "risk_level": "normal" },
    { "name": "get_payment_method_detail", "description": "Chi tiết PTTT.", "endpoint": "POST /internal/skills/get_payment_method_detail", "input_schema": { "type": "object", "required": ["pttt_id"], "properties": { "pttt_id": { "type": "string" } } }, "type": "action", "risk_level": "read" },
    { "name": "test_payment_method", "description": "Test PTTT (VietQR generate).", "endpoint": "POST /internal/skills/test_payment_method", "input_schema": { "type": "object", "required": ["pttt_id", "amount"], "properties": { "pttt_id": { "type": "string" }, "amount": { "type": "number" } } }, "type": "action", "risk_level": "normal" }
  ]
}
